scriptworker/__init__.py
scriptworker/artifacts.py
scriptworker/client.py
scriptworker/config.py
scriptworker/constants.py
scriptworker/context.py
scriptworker/ed25519.py
scriptworker/exceptions.py
scriptworker/github.py
scriptworker/log.py
scriptworker/task.py
scriptworker/task_process.py
scriptworker/utils.py
scriptworker/worker.py
scriptworker/cot/__init__.py
scriptworker/cot/generate.py
scriptworker/cot/verify.py
scriptworker/data/cot_v1_schema.json
scriptworker/data/scriptworker_task_schema.json
scriptworker-62.3.0.dist-info/METADATA
scriptworker-62.3.0.dist-info/WHEEL
scriptworker-62.3.0.dist-info/entry_points.txt
scriptworker-62.3.0.dist-info/licenses/LICENSE
scriptworker-62.3.0.dist-info/RECORD
