Metadata-Version: 2.4
Name: scriptworker
Version: 62.3.0
Summary: Taskcluster scriptworker
Author-email: Mozilla Release Engineering <releng@mozilla.com>
License-File: LICENSE
Classifier: Intended Audience :: Developers
Classifier: Natural Language :: English
Classifier: Programming Language :: Python :: 3.11
Classifier: Programming Language :: Python :: 3.12
Classifier: Programming Language :: Python :: 3.13
Requires-Python: >=3.11
Requires-Dist: aiohttp>=3
Requires-Dist: aiomemoizettl
Requires-Dist: arrow>=1.0
Requires-Dist: cryptography>=2.6.1
Requires-Dist: dictdiffer
Requires-Dist: github3-py
Requires-Dist: immutabledict>=1.3.0
Requires-Dist: json-e>=2.5.0
Requires-Dist: jsonschema[format-nongpl]
Requires-Dist: pyyaml
Requires-Dist: taskcluster-taskgraph
Requires-Dist: taskcluster>=40
